{"cameraMode":{"drawMode":0,"name":"Shaded","section":"Shading Mode"},"sceneLighting":true,"audioPlay":false,"sceneViewState":{"m_AlwaysRefresh":false,"showFog":true,"showSkybox":true,"showFlares":true,"showImageEffects":true,"showParticleSystems":true,"showVisualEffectGraphs":true,"m_FxEnabled":true},"in2DMode":false,"pivot":{"x":17.242542266845704,"y":-10.470645904541016,"z":47.76902770996094},"rotation":{"x":0.3883543014526367,"y":0.11728931218385697,"z":-0.049903977662324908,"w":0.9126598238945007},"size":40.342811584472659,"orthographic":false}